MANIFEST.in
README.md
setup.py
micros2client/__init__.py
micros2client/cli_parser.py
micros2client/client.py
micros2client.egg-info/PKG-INFO
micros2client.egg-info/SOURCES.txt
micros2client.egg-info/dependency_links.txt
micros2client.egg-info/not-zip-safe
micros2client.egg-info/requires.txt
micros2client.egg-info/top_level.txt
micros2client/configs/__init__.py
micros2client/configs/config_cli.py
micros2client/configs/config_handler.py
micros2client/tests/__init__.py
micros2client/tests/base_tests.py