Metadata-Version: 1.0
Name: micros2client
Version: 1
Summary: python and cli Client for providing  access to micros2 microservice after authtication from tokenleader
Home-page: https://github.com/microservice-tsp-billing/micros2lient
Author: Bhujay Kumar Bhatta
Author-email: bhujay.bhatta@yahoo.com
License: Apache Software License
Platform: UNKNOWN
